Metadata-Version: 2.4
Name: statick
Version: 0.13.0
Summary: Making code quality easier.
Maintainer-email: Thomas Denewiler <tdenewiler@gmail.com>, Alexander Xydes <axydes@gmail.com>, Greg Kogut <gregkogut@gmail.com>
License: CC0-1.0
Project-URL: Homepage, https://github.com/triboelectric/statick
Project-URL: Bug Tracker, https://github.com/triboelectric/statick/issues
Classifier: License :: CC0 1.0 Universal (CC0 1.0) Public Domain Dedication
Classifier: Programming Language :: Python :: 3
Classifier: Programming Language :: Python :: 3.9
Classifier: Programming Language :: Python :: 3.10
Classifier: Programming Language :: Python :: 3.11
Classifier: Programming Language :: Python :: 3.12
Classifier: Programming Language :: Python :: 3.13
Classifier: Topic :: Software Development :: Testing
Requires-Python: >=3.9
License-File: LICENSE
Requires-Dist: PyYAML
Requires-Dist: bandit
Requires-Dist: black
Requires-Dist: cmakelint
Requires-Dist: cpplint
Requires-Dist: docformatter
Requires-Dist: flawfinder
Requires-Dist: importlib_metadata
Requires-Dist: importlib_metadata
Requires-Dist: isort
Requires-Dist: lizard
Requires-Dist: mypy
Requires-Dist: packaging
Requires-Dist: pycodestyle
Requires-Dist: pydocstyle
Requires-Dist: pyflakes
Requires-Dist: pylint
Requires-Dist: pyright
Requires-Dist: restructuredtext-lint
Requires-Dist: rstcheck
Requires-Dist: ruff>=0.0.237
Requires-Dist: sphinx
Requires-Dist: tabulate
Requires-Dist: types-PyYAML
Requires-Dist: types-docutils
Requires-Dist: types-setuptools
Requires-Dist: types-tabulate
Requires-Dist: xmltodict
Requires-Dist: yamllint
Provides-Extra: test
Requires-Dist: coverage; extra == "test"
Requires-Dist: lark; extra == "test"
Requires-Dist: mock; extra == "test"
Requires-Dist: pytest; extra == "test"
Requires-Dist: pytest-cov; extra == "test"
Requires-Dist: tox; extra == "test"
Requires-Dist: tox-gh-actions; extra == "test"
Requires-Dist: tox-uv; extra == "test"
Provides-Extra: docs
Requires-Dist: sphinx; extra == "docs"
Requires-Dist: yaml-1.3; extra == "docs"
Dynamic: license-file
